clrmagic.dll
clrmagic.py
clrmagic-0.0.1a2.dist-info/DESCRIPTION.rst
clrmagic-0.0.1a2.dist-info/METADATA
clrmagic-0.0.1a2.dist-info/RECORD
clrmagic-0.0.1a2.dist-info/WHEEL
clrmagic-0.0.1a2.dist-info/metadata.json
clrmagic-0.0.1a2.dist-info/top_level.txt
